Workbook

Sheet CORTE MAYO - 24
B2: LATIN AMERICAN MOTORCYCLE ASSOCIATION
B3: CAPITULO LAMA MEDELLIN
B4: "¡HERMAN@S PARA HACER HERMAN@S!"
A6: INFORME DE TESORERIA - CORTE JUNIO 4 / 2024
A8: FECHA | B8: CONCEPTO | C8: INGRESOS | D8: EGRESOS | E8: SALDO
B9: ENTREGA DINERO POR PARTE DEL PRESIDENTE | C9: 2000000
B10: PAGO MENSUALIDADES ENERO A JUNIO CAMILO ORTEGON | C10: 60000
B11: PAGO MENSUALIDADES ENERO A JUNIO MARIO JIMENEZ | C11: 60000
B17: TOTAL | C17: =SUM(C9:C16) -> 2120000 | D17: =SUM(D9:D16) -> 0 | E17: =SUM(E9:E16) -> 0
B19: SALDO EFECTIVO MES ANTERIOR | C19: =+E9 -> 0
B20: INGRESOS | C20: =C17 -> 2120000
B21: Dólares | C21: U$ 135
B23: TOTAL INGRESOS | C23: =SUM(C19:C22) -> 2120000
B24: EGRESOS | C24: =+D17 -> 0
B26: SALDO EN TESORERIA A LA FECHA | C26: =C23-C25 -> 2120000
B29: MARIO ALBERTO JIMENEZ PARRA
B30: TESORERO LAMA MEDELLIN

Sheet CORTE JUNIO-4-24
B2: LATIN AMERICAN MOTORCYCLE ASSOCIATION
B3: CAPITULO LAMA MEDELLIN
B4: "¡HERMAN@S PARA HACER HERMAN@S!"
A6: INFORME DE TESORERIA - CORTE JUNIO 4 / 2024
A8: FECHA | B8: CONCEPTO | C8: INGRESOS | D8: EGRESOS | E8: SALDO
B9: SALDO MES ANTERIOR EFECTIVO | E9: 2120000
A10: 45439 | B10: PAGO MENSUALIDADES ENERO A MAYO CARLOS MARIO DIAZ | C10: 50000
A11: 45439 | B11: PAGO PARCHE MEMBRESIA AÑO 2024 CARLOS MARIO DIAZ | C11: 80000
A12: 45436 | B12: PAGO CAMISETAS LAMA MEDELLIN CAMILO ORTEGON | C12: 110000
B17: TOTAL | C17: =SUM(C9:C16) -> 240000 | D17: =SUM(D9:D16) -> 0 | E17: 2360000
B19: SALDO EFECTIVO MES ANTERIOR | C19: =+E9 -> 2120000
B20: INGRESOS | C20: =C17 -> 240000
B21: Dólares | C21: U$ 135
B23: TOTAL INGRESOS | C23: =SUM(C19:C22) -> 2360000
B24: EGRESOS | C24: =+D17 -> 0
B25: EFECTIVO MILTON FALTANTE POR CONSIGNAR | C25: 1853637
B26: SALDO EN TESORERIA A LA FECHA | C26: 2360000
B29: MARIO ALBERTO JIMENEZ PARRA
B30: TESORERO LAMA MEDELLIN

Sheet CORTE JULIO 4 -24
B2: LATIN AMERICAN MOTORCYCLE ASSOCIATION
B3: CAPITULO LAMA MEDELLIN
B4: "¡HERMAN@S PARA HACER HERMAN@S!"
A6: INFORME DE TESORERIA - CORTE JULIO 04 / 2024
A8: FECHA | B8: CONCEPTO | C8: INGRESOS | D8: EGRESOS | E8: SALDO
B9: SALDO EFECTIVO MES ANTERIOR | E9: 2360000
A10: 45454 | B10: VENTA 4 GORRAS Y 4 BALACLAVAS GIRLESA BUITRAGO | C10: 160000 | E10: =E9+C10-D10 -> 2520000
A11: 45457 | B11: CONSIGNACION MILTON GOMEZ | C11: 1853637 | E11: =E10+C11-D11 -> 4373637
A12: 45461 | B12: PAGO A CARLOS MARIO CEBALLOS EVENTO NIÑOS DIC | D12: 240000 | E12: =E11+C12-D12 -> 4133637
A13: 45461 | B13: PAGO A RAMON GONZALEZ ASISTENCIA RALLEY INTERNACIONAL | D13: 60000 | E13: =E12+C13-D13 -> 4073637
A14: 45461 | B14: PAGO A JHON JARVEY GOMEZ ASISTENCIA RALLEY INTERNACIONAL | D14: 60000 | E14: =E13+C14-D14 -> 4013637
A15: 45461 | B15: PAGO ASISTENCIA LAMA HIERRO CARLOS ALBERTO ARAQUE | D15: 60000 | E15: =E14+C15-D15 -> 3953637
A16: 45461 | B16: PAGO ASISTENCIA LAMA HIERRO CARLOS YEFERSON MONTOYA | D16: 60000 | E16: =E15+C16-D16 -> 3893637
A17: 45461 | B17: PAGO A YEFERSON USUGA ASISTENCIA RALLEY INTERNACIONAL | D17: 60000 | E17: =E16+C17-D17 -> 3833637
A18: 45461 | B18: PAGO HECTOR MARIO GONZALEZ ASISTENCIA RALLEY INTERNACIONAL | D18: 60000 | E18: =E17+C18-D18 -> 3773637
A19: 45461 | B19: PAGO ASISTENCIA RALEY INTERNACIONAL CAPA | D19: 60000 | E19: =E18+C19-D19 -> 3713637
A20: 45461 | B20: RECAUDO MENSUALIDAD JUL-AGO -SEP RAMON GONZALEZ | C20: 60000 | E20: =E19+C20-D20 -> 3773637
A21: 45461 | B21: RECAUDO MENSUALIDAD JUL-AGO -SEP JHON JARVEY GOMEZ | C21: 60000 | E21: =E20+C21-D21 -> 3833637
A22: 45461 | B22: RECAUDO MENSUALIDAD JUL-AGO -SEP CAPA | C22: 60000 | E22: =E21+C22-D22 -> 3893637
A23: 45461 | B23: RECAUDO MENSUALIDAD ENERO A JUNIO YEFERSON MONTOYA | C23: 60000 | E23: =E22+C23-D23 -> 3953637
A24: 45461 | B24: RECAUDO MENSUALIDAD JUL-AGO -SEP YEFERSON MONTOYA | C24: 60000 | E24: =E23+C24-D24 -> 4013637
A25: 45461 | B25: RECAUDO MENSUALIDAD JUL-AGO -SEP MARIO JIMENEZ | C25: 60000 | E25: =E24+C25-D25 -> 4073637
A26: 45461 | B26: RECAUDO MENSUALIDAD JUL-AGO -SEP HECTOR MARIO GONZALEZ | C26: 60000 | E26: =E25+C26-D26 -> 4133637
A27: 45461 | B27: RECAUDO MENSUALIDAD JUL-AGO -SEP YEFERSON USUGA | C27: 60000 | E27: =E26+C27-D27 -> 4193637
E28: =E27+C28-D28 -> 4193637
E29: =E28+C29-D29 -> 4193637
B30: TOTAL | C30: =SUM(C10:C29) -> 2493637 | D30: =SUM(D12:D29) -> 660000 | E30: 4193637
B33: SALDO EFECTIVO MES ANTERIOR | C33: =+E9 -> 2360000
B34: INGRESOS | C34: =C30 -> 2493637
B35: Dólares | C35: U$ 135
B36: TOTAL INGRESOS | C36: =SUM(C33:C35) -> 4853637
B37: EGRESOS | C37: =+D30 -> 660000
B38: SALDO EN TESORERIA A LA FECHA | C38: =C36-C37 -> 4193637
B41: MARIO ALBERTO JIMENEZ PARRA
B42: TESORERO LAMA MEDELLIN

Sheet CORTE AGOSTO 4 -24
B2: LATIN AMERICAN MOTORCYCLE ASSOCIATION
B3: CAPITULO LAMA MEDELLIN
B4: "¡HERMAN@S PARA HACER HERMAN@S!"
A6: INFORME DE TESORERIA - CORTE JULIO 04 / 2024
A8: FECHA | B8: CONCEPTO | C8: INGRESOS | D8: EGRESOS | E8: SALDO
B9: SALDO EFECTIVO MES ANTERIOR | E9: 4193637
A10: 45477 | B10: RECAUDO MENSUAIDAD MAYO A DIC CARLOS MARIO DIAZ | C10: 130000 | E10: =(E9+C10)-D10 -> 4323637
A11: 45477 | B11: RECAUDO MENSUALIDAD ENERO -JUNIO ALEXANDER BETANCUR | C11: 60000 | E11: =(E10+C11)-D11 -> 4383637
A12: 45477 | B12: RECAUDO MENSUALIDAD JULIO -DICIEMBRE HERNANDO VILLADA | C12: 120000 | E12: =(E11+C12)-D12 -> 4503637
A13: 45477 | B13: RECAUDO MENSUALIDAD ENERO -JUNIO CESAR RODRIGUEZ | C13: 60000 | E13: =(E12+C13)-D13 -> 4563637
A14: 45477 | B14: RECAUDO MENSUALIDAD ENERO -JUNIO ROBINSON GALVIS | C14: 60000 | E14: =(E13+C14)-D14 -> 4623637
A15: 45477 | B15: RECAUDO MENSUALIDAD ENERO -JUNIO JUAN OSORIO | C15: 60000 | E15: =(E14+C15)-D15 -> 4683637
A16: 45477 | B16: RECAUDO ACTIVIDAD PERROS ASAMBLEA JULIO | C16: 120000 | E16: =(E15+C16)-D16 -> 4803637
A17: 45477 | B17: RECAUDO MENSUALIDAD OCT- DIC. RAMON GONZALES | C17: 60000 | E17: =(E16+C17)-D17 -> 4863637 | K17: ITEMS | L17: CANTIDAD | M17: VALOR | N17: TOTAL
A18: 45477 | B18: RECAUDO MENSUALIDAD ENE- JUN. JUAN ESTEBAN SUAREZ | C18: 60000 | E18: =(E17+C18)-D18 -> 4923637 | K18: NACIONALES | L18: 63 | M18: 15000 | N18: =L18*M18 -> 945000
A19: 45482 | B19: RECAUDO MENSUALIDAD ABR- JUN. GIRLESA BUIRAGO | C19: 50000 | E19: =(E18+C19)-D19 -> 4973637 | K19: INTERNACIONAL | L19: 152 | M19: 15000 | N19: =L19*M19 -> 2280000
A20: 45483 | B20: RECAUDO MENSUALIDAD ENE- JUL. FREDDY MARIN | C20: 80000 | E20: =(E19+C20)-D20 -> 5053637 | K20: TRANSPORTE INT | L20: 80 | M20: 30500 | N20: =L20*M20 -> 2440000
B21: RECAUDO MENSUALIDAD JUL- AGO. CAMILO ORTEGON | C21: 40000 | E21: =(E20+C21)-D21 -> 5093637 | K21: TRANSPORTE NA | L21: 40 | M21: 30500 | N21: =L21*M21 -> 1220000
B22: RECAUDO MENSUALIDAD JUL- AGO. JOSE EDINSON OSPINA | C22: 40000 | E22: =(E21+C22)-D22 -> 5133637 | K22: VENTAS GIRLESA | N22: 460000
B23: PAGO 7 INSCRIPCIONES RALLY NACIONAL | D23: 665000 | E23: =(E22+C23)-D23 -> 4468637 | N23: =N18+N19+N20+N21+N22 -> 7345000
B24: INGRESOS POR INSCRIPCIONES | C24: 3225000 | E24: =(E23+C24)-D24 -> 7693637
B25: INGRESOS POR TRANSPORTE | C25: 3660000 | E25: =(E24+C25)-D25 -> 11353637 | K25: COMPRAS | N25: 1478000
B26: PAGO TRASNPORTES BUSES SANTA FE ANTIOQUIA | D26: 3420000 | E26: =(E25+C26)-D26 -> 7933637 | K26: BUSES | N26: 3420000
B27: COMPRA DE PARCHES | D27: 900000 | E27: =(E26+C27)-D27 -> 7033637 | N27: =N25+N26 -> 4898000
B28: ALMUERZOS BAILARINES | D28: 50000 | E28: =(E27+C28)-D28 -> 6983637
B29: PEAJE TRAILER | D29: 43000 | E29: =(E28+C29)-D29 -> 6940637
B30: RECONOCIMIENTOS PIÑONES | D30: 360000 | E30: =(E29+C30)-D30 -> 6580637 | K30: SALDO | N30: =N22-N27 -> -4438000
B31: PREMIOS OTROS GANADORES COOLAR AREPAS ETC | D31: 45000 | E31: =(E30+C31)-D31 -> 6535637 | K31: PENDIENTE GERENCIA NEGOCIOS | N31: 1900000
B32: MANILLAS MARCADAS | D32: 80000 | E32: =(E31+C32)-D32 -> 6455637
B33: VENTAS GIRLESA | C33: 460000 | E33: =(E32+C33)-D33 -> 6915637
E34: =(E33+C34)-D34 -> 6915637
B35: TOTAL | C35: =SUM(C10:C34) -> 8285000 | D35: =SUM(D12:D34) -> 5563000 | E35: =E34 -> 6915637
B38: SALDO EFECTIVO MES ANTERIOR | C38: =E9 -> 4193637
B39: INGRESOS | C39: =C35 -> 8285000
B40: Dólares | C40: 135
B41: TOTAL INGRESOS | C41: =SUM(C38:C40) -> 12478772
B42: EGRESOS | C42: =+D35 -> 5563000
B43: SALDO EN TESORERIA A LA FECHA | C43: =C41-C42 -> 6915772
B46: MARIO ALBERTO JIMENEZ PARRA
B47: TESORERO LAMA MEDELLIN

Sheet CORTE DICIEMBRE 20 -24
B2: LATIN AMERICAN MOTORCYCLE ASSOCIATION
B3: CAPITULO LAMA MEDELLIN
B4: "¡HERMAN@S PARA HACER HERMAN@S!"
A6: INFORME DE TESORERIA - CORTE DIC 31 / 2024
A8: FECHA | B8: CONCEPTO | C8: INGRESOS | D8: EGRESOS | E8: SALDO
B9: SALDO EFECTIVO MES ANTERIOR | E9: 6915000
B10: PAGO MENSUALIDAD MARIO JIMENEZ | C10: 60000 | E10: =(E9+C10)-D10 -> 6975000
B11: SILLAS Y MESAS TRANSPORTES GASTOS PARA ANIVERSARIO | D11: 380000 | E11: =(E10+C11)-D11 -> 6595000
B12: COMPRA DE PARCHES INTERNACIONALES | D12: 1098000 | E12: =(E11+C12)-D12 -> 5497000
B13: PAGO TRASNPORTADORA POR ENVIO PARCHES | D13: 22000 | E13: =(E12+C13)-D13 -> 5475000
B14: PAGO PARCHES MOVIE ARZUZA | C14: 253000 | E14: =(E13+C14)-D14 -> 5728000
B15: PAGO DE MENSUALIDAD ANGELA | C15: 40000 | E15: =(E14+C15)-D15 -> 5768000
B16: PAGO MENSUALIDAD MOVIE | C16: 180000 | E16: =(E15+C16)-D16 -> 5948000
B17: COMPRA 5 RECORDATORIOS 3 ARGENTINA 1 BUGA 1 PEREIRA | D17: 40000 | E17: =(E16+C17)-D17 -> 5908000
B18: PAGO HECTOR MENSUALIDAD E INSCRPCION 2025 | C18: 106000 | E18: =(E17+C18)-D18 -> 6014000
B19: PAGO ANGELA PARCHES | C19: 265800 | E19: =(E18+C19)-D19 -> 6279800
B20: MENSUALIDAD CAMILO ORTEGON | C20: 80000 | E20: =(E19+C20)-D20 -> 6359800
B21: MENSUALIDAD CARLOS ANDRES PERES | C21: 60000 | E21: =(E20+C21)-D21 -> 6419800
B22: FIESTA FIN DE AÑO | D22: 1750000 | E22: =(E21+C22)-D22 -> 4669800
B23: PAGO MENSUALIDAD EDINSON OSPINA | C23: 80000 | E23: =(E22+C23)-D23 -> 4749800
B24: PAGO MENSUALIDAD JHON HARVEY | C24: 60000 | E24: =(E23+C24)-D24 -> 4809800
B25: PAGO MENSUALIDAD CARLOS MARIO CEBALLOS | C25: 120000 | E25: =(E24+C25)-D25 -> 4929800
B26: PAGO A RAMON USO DE SALON ASAMBLEA DE ENERO | D26: 50000 | E26: =(E25+C26)-D26 -> 4879800
B27: PAGO MENSUALIDAD CESAR RODRIGUEZ | C27: 120000 | E27: =(E26+C27)-D27 -> 4999800
B28: PAGO MENSUALIDAD ROBINSON GALVIS | C28: 120000 | E28: =(E27+C28)-D28 -> 5119800
B29: PAGO MENSUALIDAD JUAN ESTEBAN SUAREZ | C29: 80000 | E29: =(E28+C29)-D29 -> 5199800
B30: PAGO MENSUALIDAD E INSCRIPCION GIRLESA BUITRAGO | C30: 80000 | E30: =(E29+C30)-D30 -> 5279800
B31: PAGO MEMBRESIA RAMON GONZALES | C31: 46000 | E31: =(E30+C31)-D31 -> 5325800
B32: PAGO MENSUALIDAD ENERO 2025 Y MEMBRESIA DANIEL | C32: 66000 | E32: =(E31+C32)-D32 -> 5391800
B33: RECAUDO CUOTA DE FIESTA FIN DE AÑO | C33: 315000 | E33: =(E32+C33)-D33 -> 5706800
B34: TOTAL | C34: =SUM(C10:C33) -> 2131800 | D34: =SUM(D10:D33) -> 3340000 | E34: =E33 -> 5706800
B37: SALDO EFECTIVO MES ANTERIOR | C37: =E9 -> 6915000
B38: INGRESOS | C38: =C34 -> 2131800
B39: Dólares | C39: 135
B40: TOTAL INGRESOS | C40: =C37+C38 -> 9046800
B41: EGRESOS | C41: =+D34 -> 3340000
B42: SALDO EN TESORERIA A LA FECHA | C42: =E34 -> 5706800
B45: MARIO ALBERTO JIMENEZ PARRA
B46: TESORERO LAMA MEDELLIN

Sheet CORTE FEBRERO 28-25
B2: LATIN AMERICAN MOTORCYCLE ASSOCIATION
B3: CAPITULO LAMA MEDELLIN
B4: "¡HERMAN@S PARA HACER HERMAN@S!"
A6: INFORME DE TESORERIA - CORTE FEB 28 / 2025
A8: FECHA | B8: CONCEPTO | C8: INGRESOS | D8: EGRESOS | E8: SALDO
B9: SALDO EFECTIVO MES ANTERIOR | E9: ='CORTE DICIEMBRE 20 -24'!C42 -> 5706800
B10: PAGO MEMBRESIA ESPOSA DE DANIEL VILLAMIZAR | C10: 46000 | E10: =(E9+C10)-D10 -> 5752800
B11: PAGO MENSUALIDAD FEB- DIC DANIEL VILLAMIZAR | C11: 220000 | E11: =(E10+C11)-D11 -> 5972800
B12: PAGO MEMBRESIA JHON ARZUZA | C12: 46000 | E12: =(E11+C12)-D12 -> 6018800
B13: PAGO MEMBRESIA CARLOS JULIO MOVIE | C13: 46000 | E13: =(E12+C13)-D13 -> 6064800
B14: PAGO MEMBRESIA Y MENSUAIDAD ENERO ANGELA MARIA | C14: 66000 | E14: =(E13+C14)-D14 -> 6130800
B15: PAGO MEMBRESIA MARIO JIMENEZ | C15: 92000 | E15: =(E14+C15)-D15 -> 6222800
B16: PAGO MEMBRESIA JHON DAVID SANCHEZ TIIN | C16: 46000 | E16: =(E15+C16)-D16 -> 6268800
B17: PAGO MEMBRESIA JHON JARVEY | C17: 92000 | E17: =(E16+C17)-D17 -> 6360800
B18: PAGO MEMBRESIA CAMILO ORTEGON | C18: 46000 | E18: =(E17+C18)-D18 -> 6406800
B19: PAGO MEMBRESIA YEFERSON USUGA | C19: 46000 | E19: =(E18+C19)-D19 -> 6452800
B20: PAGO MEMBRESIA JEFERSON MONTOYA | C20: 45000 | E20: =(E19+C20)-D20 -> 6497800
B21: PAGO MENSUALIDAD ENERO GIRLESA | C21: 20000 | E21: =(E20+C21)-D21 -> 6517800
... B25: PAGO MEMBRESIA ROBINSON GALVEZ | C25: 92000 | E25: =(E24+C25)-D25 -> 7153800
B26: COMPRA MUESTRA RECONOCIMIENTO | D26: 50000 | E26: =(E25+C26)-D26 -> 7103800
B27: COMPRA DE MEMBRESIAS | D27: 2251622 | E27: =(E26+C27)-D27 -> 4852178
B28: PAGO TRASNPORTADORA MEMBRESIAS | D28: 16500 | E28: =(E27+C28)-D28 -> 4835678
B29: PAGO ALQUILER DE FINCA FIESTA FIN DE AÑO | D29: 200000 | E29: =(E28+C29)-D29 -> 4635678
B30: COMPRA 5 RECORDATORIOS | D30: 250000 | E30: =(E29+C30)-D30 -> 4385678
B31: PAGO DE PARCHES DANIEL VILLAMIZAR | C31: 128800 | E31: =(E30+C31)-D31 -> 4514478
B32: PAGO MENSUALIDAD FEBRERO ANGELA | C32: 20000 | E32: =(E31+C32)-D32 -> 4534478
B33: TOTAL | C33: =SUM(C10:C32) -> 1595800 | D33: =SUM(D9:D32) -> 2768122 | E33: =E32 -> 4534478
B36: SALDO EFECTIVO MES ANTERIOR | C36: =E9 -> 5706800
B37: INGRESOS | C37: =C33 -> 1595800
B38: dolares | C38: 135
B39: TOTAL INGRESOS | C39: =C36+C37 -> 7302600
B40: EGRESOS | C40: =+D33 -> 2768122
B41: SALDO EN TESORERIA A LA FECHA | C41: =E33 -> 4534478
B44: MARIO ALBERTO JIMENEZ PARRA
B45: TESORERO LAMA MEDELLIN

Sheet CORTE MARZO 31-25
B2: LATIN AMERICAN MOTORCYCLE ASSOCIATION
B3: CAPITULO LAMA MEDELLIN
B4: "¡HERMAN@S PARA HACER HERMAN@S!"
A6: INFORME DE TESORERIA - CORTE MAR 31 / 2025
A8: FECHA | B8: CONCEPTO | C8: INGRESOS | D8: EGRESOS | E8: SALDO
B9: SALDO EFECTIVO MES ANTERIOR | E9: ='CORTE DICIEMBRE 20 -24'!C42 -> 5706800
B10: PAGO MEMBRESIA ESPOSA DE DANIEL VILLAMIZAR | C10: 46000 | E10: =(E9+C10)-D10 -> 5752800
B11: PAGO MENSUALIDAD FEB- DIC DANIEL VILLAMIZAR | C11: 220000 | E11: =(E10+C11)-D11 -> 5972800
B12: PAGO MEMBRESIA JHON ARZUZA | C12: 46000 | E12: =(E11+C12)-D12 -> 6018800
B13: PAGO MEMBRESIA CARLOS JULIO MOVIE | C13: 46000 | E13: =(E12+C13)-D13 -> 6064800
B14: PAGO MEMBRESIA Y MENSUAIDAD ENERO ANGELA MARIA | C14: 66000 | E14: =(E13+C14)-D14 -> 6130800
B15: PAGO MEMBRESIA MARIO JIMENEZ | C15: 92000 | E15: =(E14+C15)-D15 -> 6222800
B16: PAGO MEMBRESIA JHON DAVID SANCHEZ TIIN | C16: 46000 | E16: =(E15+C16)-D16 -> 6268800
B17: PAGO MEMBRESIA JHON JARVEY | C17: 92000 | E17: =(E16+C17)-D17 -> 6360800
B18: PAGO MEMBRESIA CAMILO ORTEGON | C18: 46000 | E18: =(E17+C18)-D18 -> 6406800
B19: PAGO MEMBRESIA YEFERSON USUGA | C19: 46000 | E19: =(E18+C19)-D19 -> 6452800
B20: PAGO MEMBRESIA JEFERSON MONTOYA | C20: 45000 | E20: =(E19+C20)-D20 -> 6497800
B21: PAGO MENSUALIDAD ENERO GIRLESA | C21: 20000 | E21: =(E20+C21)-D21 -> 6517800
... B25: PAGO MEMBRESIA ROBINSON GALVEZ | C25: 92000 | E25: =(E24+C25)-D25 -> 7153800
B26: COMPRA MUESTRA RECONOCIMIENTO | D26: 50000 | E26: =(E25+C26)-D26 -> 7103800
B27: COMPRA DE MEMBRESIAS | D27: 2251622 | E27: =(E26+C27)-D27 -> 4852178
B28: PAGO TRASNPORTADORA MEMBRESIAS | D28: 16500 | E28: =(E27+C28)-D28 -> 4835678
B29: PAGO ALQUILER DE FINCA FIESTA FIN DE AÑO | D29: 200000 | E29: =(E28+C29)-D29 -> 4635678
B30: COMPRA 5 RECORDATORIOS | D30: 250000 | E30: =(E29+C30)-D30 -> 4385678
B31: PAGO DE PARCHES DANIEL VILLAMIZAR | C31: 128800 | E31: =(E30+C31)-D31 -> 4514478
B32: PAGO MENSUALIDAD FEBRERO ANGELA | C32: 20000 | E32: =(E31+C32)-D32 -> 4534478
B33: TOTAL | C33: =SUM(C10:C32) -> 1595800 | D33: =SUM(D10:D32) -> 2768122 | E33: =E32 -> 4534478
B36: SALDO EFECTIVO MES ANTERIOR | C36: =E9 -> 5706800
B37: INGRESOS | C37: =C33 -> 1595800
B38: dolares | C38: 165
B39: TOTAL INGRESOS | C39: =C36+C37 -> 7302600
B40: EGRESOS | C40: =+D33 -> 2768122
B41: SALDO EN TESORERIA A LA FECHA | C41: =E33 -> 4534478
B44: MARIO ALBERTO JIMENEZ PARRA
B45: TESORERO LAMA MEDELLIN

Sheet CORTE ABRIL 30-25 
B2: LATIN AMERICAN MOTORCYCLE ASSOCIATION
B3: CAPITULO LAMA MEDELLIN
B4: "¡HERMAN@S PARA HACER HERMAN@S!"
A6: INFORME DE TESORERIA - CORTE ABR 30 / 2025
A8: FECHA | B8: CONCEPTO | C8: INGRESOS | D8: EGRESOS | E8: SALDO
B9: SALDO EFECTIVO MES ANTERIOR | E9: ='CORTE MARZO 31-25'!C41 -> 4534478
E10: =(E9+C10)-D10 -> 4534478 | G10: Saldo deseado | H10: =C41+H11 -> 4517445.5
E11: =(E10+C11)-D11 -> 4534478 | G11: Pendiente por cobrar | H11: =SUM(C10:C15) -> 0 | I11: Pendiente de recibir por parte de tesoreria a miembros
E12: =(E11+C12)-D12 -> 4534478 | G12: Saldo real actual | H12: =H10-H11 -> 4517445.5
E13: =(E12+C13)-D13 -> 4534478
E14: =(E13+C14)-D14 -> 4534478
E15: =(E14+C15)-D15 -> 4534478
B16: PAGO MEMBRESIA MILTON GOMEZ | C16: 72000 | E16: =(E15+C16)-D16 -> 4606478
B17: COMPRA DE 5 * 20 USD MEMBRESIAS TRM 4.387,98 | D17: 438798 | E17: =(E16+C17)-D17 -> 4167680
B18: COMPRA PARCHES 176 USD (1 COLOMBIA ASSOCIATE APPLICATION FEE + 2 2025 INTERNATIONAL SPOUSAL MEMBERSHIP RENEWAL + 1 FIRST YEAR INTERNATIONAL PATCHES + 1 COLOMBIA COUNTRY WING + 1 COLOMBIA COUTRY PATCH + 1 CHAPTER CITY PATCH + 1 COLOMBIA STATE PATCH + 1 COLOMBIA COUNTRY FLAG + 3 DAMA PATCH TRM 4.387,98) | D18: 772284.48 | E18: =(E17+C18)-D18 -> 3395395.5
B19: PAGO TRASNPORTADORA MEMBRESIAS | D19: 16500 | E19: =(E18+C19)-D19 -> 3378895.5
B20: VENTA 165 DOLARES 25/03 A 3,970 | C20: 655050 | E20: =(E19+C20)-D20 -> 4033945.5
B21: PAGO TRANSPORTADORA INTERRAPIDISIMO | D21: 16500 | E21: =(E20+C21)-D21 -> 4017445.5
B22: VENTA 8 CAMISETAS | C22: 480000 | E22: =(E21+C22)-D22 -> 4497445.5
B23: VENTA 1 BUFF | C23: 20000 | E23: =(E22+C23)-D23 -> 4517445.5
E24: =(E23+C24)-D24 -> 4517445.5
E25: =(E24+C25)-D25 -> 4517445.5
E26: =(E25+C26)-D26 -> 4517445.5
E27: =(E26+C27)-D27 -> 4517445.5
E28: =(E27+C28)-D28 -> 4517445.5
E29: =(E28+C29)-D29 -> 4517445.5
E30: =(E29+C30)-D30 -> 4517445.5
E31: =(E30+C31)-D31 -> 4517445.5
E32: =(E31+C32)-D32 -> 4517445.5
B33: TOTAL | C33: =SUM(C10:C32) -> 1227050 | D33: =SUM(D10:D32) -> 1244082.5 | E33: =E32 -> 4517445.5
B36: SALDO EFECTIVO MES ANTERIOR | C36: =E9 -> 4534478
B37: INGRESOS | C37: =C33 -> 1227050
B38: dolares
B39: TOTAL INGRESOS | C39: =C36+C37 -> 5761528
B40: EGRESOS | C40: =+D33 -> 1244082.5
B41: SALDO EN TESORERIA A LA FECHA | C41: =E33-H11 -> 4517445.5
B44: DANIEL VILLAMIZAR ARAQUE
B45: TESORERO ADHOC LAMA MEDELLIN

Sheet CORTE MAYO 31-25
H1: (
B2: LATIN AMERICAN MOTORCYCLE ASSOCIATION
B3: CAPITULO LAMA MEDELLIN
B4: "¡HERMAN@S PARA HACER HERMAN@S!"
A6: INFORME DE TESORERIA - CORTE MAY 31 / 2025
A8: FECHA | B8: CONCEPTO | C8: INGRESOS | D8: EGRESOS | E8: SALDO
B9: SALDO EFECTIVO MES ANTERIOR | E9: ='CORTE ABRIL 30-25 '!C41 -> 4517445.5 | G9: Saldo Real Anterior | H9: ='CORTE ABRIL 30-25 '!H12 -> 4517445.5
E10: =(E9)-D10 -> 4517445.5 | G10: Pendiente por cobrar | H10: =C10+'CORTE ABRIL 30-25 '!H11 -> 0
B11: COMPRA TORTA CUMPLEAÑOS TRIMESTRE | D11: 90000 | E11: =(E10+C11)-D11 -> 4427445.5 | G11: Ingreso del mes | H11: =C12 -> 60000
B12: VENTA 1 CAMISETA JULIÁN | C12: 60000 | E12: =(E11+C12)-D12 -> 4487445.5 | G12: Saldo Real Actual | H12: =H9+H11-D33 -> 4470945.5
B13: PAGO TRANSPORTADORA INTERRAPIDISIMO 4 Parches MEMBRESIA | D13: 16500 | E13: =(E12+C13)-D13 -> 4470945.5
E14: =(E13+C14)-D14 -> 4470945.5
E15: =(E14+C15)-D15 -> 4470945.5
E16: =(E15+C16)-D16 -> 4470945.5
E17: =(E16+C17)-D17 -> 4470945.5
E18: =(E17+C18)-D18 -> 4470945.5
E19: =(E18+C19)-D19 -> 4470945.5
E20: =(E19+C20)-D20 -> 4470945.5
E21: =(E20+C21)-D21 -> 4470945.5
E22: =(E21+C22)-D22 -> 4470945.5
E23: =(E22+C23)-D23 -> 4470945.5
E24: =(E23+C24)-D24 -> 4470945.5
E25: =(E24+C25)-D25 -> 4470945.5
... E32: =(E31+C32)-D32 -> 4470945.5
B33: TOTAL | C33: =SUM(C10:C32) -> 60000 | D33: =SUM(D10:D32) -> 106500 | E33: =E32 -> 4470945.5
B36: SALDO EFECTIVO MES ANTERIOR | C36: =E9 -> 4517445.5
B37: INGRESOS | C37: =C33 -> 60000
B38: dolares
B39: TOTAL INGRESOS | C39: =C36+C37 -> 4577445.5
B40: EGRESOS | C40: =+D33 -> 106500
B41: SALDO EN TESORERIA A LA FECHA | C41: =E33 -> 4470945.5
B44: DANIEL VILLAMIZAR ARAQUE
B45: TESORERO ADHOC LAMA MEDELLIN

Sheet CORTE JUNIO 30-25
B2: LATIN AMERICAN MOTORCYCLE ASSOCIATION
B3: CAPITULO LAMA MEDELLIN
B4: "¡HERMAN@S PARA HACER HERMAN@S!"
A6: INFORME DE TESORERIA - CORTE JUN 30 / 2025
A8: FECHA | B8: CONCEPTO | C8: INGRESOS | D8: EGRESOS | E8: SALDO
B9: SALDO EFECTIVO MES ANTERIOR | E9: ='CORTE MAYO 31-25'!C41 -> 4470945.5
E10: =(E9+C10)-D10 -> 4470945.5 | I10: Saldo Real Anterior | J10: ='CORTE MAYO 31-25'!H12 -> 4470945.5 | K10: Saldo real a entregar a Tesorera
E11: =(E10+C11)-D11 -> 4470945.5 | I11: Pendiente por cobrar | J11: =SUM('CORTE MAYO 31-25'!H10) -> 0 | K11: Pendiente de recibir por parte de tesoreria a miembros
E12: =(E11+C12)-D12 -> 4470945.5 | I12: Saldo real actual | J12: 4423867 | K12: consignacion a la cuenta de la junta
E13: =(E12+C13)-D13 -> 4470945.5
E14: =(E13+C14)-D14 -> 4470945.5
E15: =(E14+C15)-D15 -> 4470945.5 | I15: Saldo con el que quedaria el capitulo al recibir pendientes por parte de algunos miembros | J15: =SUM(J11:J12) -> 4423867
E16: =(E15+C16)-D16 -> 4470945.5
E17: =(E16+C17)-D17 -> 4470945.5 | I17: Diferencias entre saldo real y consignación | J17: =J10-J12 -> 47078.52
E18: =(E17+C18)-D18 -> 4470945.5
E19: =(E18+C19)-D19 -> 4470945.5
E20: =(E19+C20)-D20 -> 4470945.5
E21: =(E20+C21)-D21 -> 4470945.5
E22: =(E21+C22)-D22 -> 4470945.5
E23: =(E22+C23)-D23 -> 4470945.5
E24: =(E23+C24)-D24 -> 4470945.5
E25: =(E24+C25)-D25 -> 4470945.5
E26: =(E25+C26)-D26 -> 4470945.5
E27: =(E26+C27)-D27 -> 4470945.5
E28: =(E27+C28)-D28 -> 4470945.5
E29: =(E28+C29)-D29 -> 4470945.5
... E32: =(E31+C32)-D32 -> 4470945.5
B33: TOTAL | C33: =SUM(C10:C32) -> 0 | D33: =SUM(D9:D32) -> 0 | E33: =E32 -> 4470945.5
B36: SALDO EFECTIVO MES ANTERIOR | C36: =E9 -> 4470945.5
B37: INGRESOS | C37: =C33 -> 0
B38: dolares
B39: TOTAL INGRESOS | C39: =C36+C37 -> 4470945.5
B40: EGRESOS | C40: =+D33 -> 0
B41: SALDO EN TESORERIA A LA FECHA | C41: =E33 -> 4470945.5
B44: DANIEL VILLAMIZAR ARAQUE
B45: TESORERO ADHOC LAMA MEDELLIN

Sheet CORTE JULIO 31-25
B2: LATIN AMERICAN MOTORCYCLE ASSOCIATION
B3: CAPITULO LAMA MEDELLIN
B4: "¡HERMAN@S PARA HACER HERMAN@S!"
A6: INFORME DE TESORERIA - CORTE JUL 31 / 2025
A8: FECHA | B8: CONCEPTO | C8: INGRESOS | D8: EGRESOS | E8: SALDO
B9: SALDO EFECTIVO MES ANTERIOR | E9: ='CORTE JUNIO 30-25'!C41 -> 4470945.5
B10: Inscripciones Pagas - Julio | C10: =3500000 -> 3500000 | D10: 0 | E10: =(E9+C10)-D10 -> 7970945.5
A11: 45854 | B11: Abono Banquete | C11: 0 | D11: 1000000 | E11: =(E10+C11)-D11 -> 6970945.5
A12: 45869 | B12: Abono Jersy's | C12: 0 | D12: 2672000 | E12: =(E11+C12)-D12 -> 4298945.5
A13: 45861 | B13: Pago - Recordatorio Parches | C13: 0 | D13: 395000 | E13: =(E12+C13)-D13 -> 3903945.5
A14: 45869 | B14: Abono Jersy's | C14: 0 | D14: 2762000 | E14: =(E13+C14)-D14 -> 1141945.5
B15: TOTAL | C15: =SUM(C9:C14) -> 3500000 | D15: =SUM(D10:D14) -> 6829000 | E15: =E14 -> 1141945.5
B18: SALDO EFECTIVO MES ANTERIOR | C18: =E9 -> 4470945.5
B19: INGRESOS | C19: =C15 -> 3500000
B20: dolares
B21: TOTAL INGRESOS | C21: =C18+C19 -> 7970945.5
B22: EGRESOS | C22: =+D15 -> 6829000
B23: SALDO EN TESORERIA A LA FECHA | C23: =E15 -> 1141945.5
B26: ANGELA MARIA RODRIGUEZ
B27: TESORERO LAMA MEDELLIN

Sheet CORTE AGOSTO 31-25
B2: LATIN AMERICAN MOTORCYCLE ASSOCIATION
B3: CAPITULO LAMA MEDELLIN
B4: "¡HERMAN@S PARA HACER HERMAN@S!"
A6: INFORME DE TESORERIA - CORTE AGO 30 / 2025
A8: FECHA | B8: CONCEPTO | C8: INGRESOS | D8: EGRESOS | E8: SALDO
B9: SALDO EFECTIVO MES ANTERIOR | E9: ='CORTE JULIO 31-25'!C23 -> 1141945.5
B10: Inscripciones Pagas, Jersey's, Donaciones - Agosto | C10: 3980000 | D10: 0 | E10: =(E9+C10)-D10 -> 5121945.5
A11: 45870 | B11: Devolución Jersey's | C11: 101000 | D11: 0 | E11: =(E10+C11)-D11 -> 5222945.5
A12: 45870 | B12: Abono Banquete #2 | C12: 0 | D12: 1000000 | E12: =(E11+C12)-D12 -> 4222945.5
A13: 45870 | B13: Reconocimientos Visitantes | C13: 0 | D13: 362000 | E13: =(E12+C13)-D13 -> 3860945.5
A14: 45872 | B14: Reintegro Pagos - Efectivo | C14: 0 | D14: 281500 | E14: =(E13+C14)-D14 -> 3579445.5
A15: 45873 | B15: Cancelación Total Banquete | C15: 0 | D15: 1546300 | E15: =(E14+C15)-D15 -> 2033145.5
A16: 45873 | B16: Pago Veracruz Estéreo | C16: 0 | D16: 1000000 | E16: =(E15+C16)-D16 -> 1033145.5
A17: 45873 | B17: Inscripciones Efectivo - Agosto 4 | C17: 860000 | D17: 0 | E17: =(E16+C17)-D17 -> 1893145.5
B18: TOTAL | C18: =SUM(C10:C17) -> 4941000 | D18: =SUM(D10:D17) -> 4189800 | E18: =E17 -> 1893145.5
B21: SALDO EFECTIVO MES ANTERIOR | C21: =E9 -> 1141945.5
B22: INGRESOS | C22: =C18 -> 4941000
B23: dolares | C23: 0
B24: TOTAL INGRESOS | C24: =C21+C22 -> 6082945.5
B25: EGRESOS | C25: =+D18 -> 4189800
B26: SALDO EN TESORERIA A LA FECHA | C26: =E18 -> 1893145.5
B29: ANGELA MARIA RODRIGUEZ
B30: TESORERO LAMA MEDELLIN

Sheet CORTE SEPTIEMBRE 11-25 
B2: LATIN AMERICAN MOTORCYCLE ASSOCIATION
B3: CAPITULO LAMA MEDELLIN
B4: "¡HERMAN@S PARA HACER HERMAN@S!"
A6: INFORME DE TESORERIA - CORTE SEP 30 / 2025
A8: FECHA | B8: CONCEPTO | C8: INGRESOS | D8: EGRESOS | E8: SALDO
B9: SALDO EFECTIVO MES ANTERIOR | E9: ='CORTE AGOSTO 31-25'!C26 -> 1893145.5 | I9: Total Consignado - Junio 2025 | J9: ='CORTE JUNIO 30-25'!J12 -> 4423867
B10: Consignaciones - Inscripciones | C10: 1620000 | D10: 0 | E10: =(E9+C10)-D10 -> 3513145.5 | I10: Pendiente por cobro | J10: 690737
B11: Intereses corrientes - Cuenta Ahorros | C11: 11975 | D11: 0 | E11: =(E10+C11)-D11 -> 3525120.5
A12: 45910 | B12: Mensualidad E Inscripción Cesar | C12: 360000 | D12: 0 | E12: =(E11+C12)-D12 -> 3885120.5 | I12: Saldo a la fecha | J12: 4718042
A13: 45911 | B13: Mensualidad Angela Maria | C13: 140000 | D13: 0 | E13: =(E12+C13)-D13 -> 4025120.5
A14: 45911 | B14: Venta Parches LAMA | C14: 140000 | D14: 0 | E14: =(E13+C14)-D14 -> 4165120.5
A15: 45911 | B15: Venta Jersey's LAMA | C15: 600000 | D15: 0 | E15: =(E14+C15)-D15 -> 4765120.5
B16: Faltante | D16: 47079 | E16: =(E15+C16)-D16 -> 4718041.5
B17: TOTAL | C17: =SUM(C12:C15) -> 1240000 | D17: =SUM(D9:D16) -> 47079 | E17: =E16 -> 4718041.5
B20: SALDO EFECTIVO MES ANTERIOR | C20: =E9 -> 1893145.5
B21: INGRESOS | C21: =C17 -> 1240000
B22: dolares | C22: 0
B23: TOTAL INGRESOS | C23: =C20+C21 -> 3133145.5
B24: EGRESOS | C24: =+D17 -> 47079
B25: SALDO EN TESORERIA A LA FECHA | C25: =E17 -> 4718041.5
B28: ANGELA MARIA RODRIGUEZ
B29: TESORERO LAMA MEDELLIN

Sheet CORTE OCTUBRE 15-25 
B2: LATIN AMERICAN MOTORCYCLE ASSOCIATION
B3: CAPITULO LAMA MEDELLIN
B4: "¡HERMAN@S PARA HACER HERMAN@S!"
A6: INFORME DE TESORERIA - CORTE OCT 31 / 2025
A8: FECHA | B8: CONCEPTO | C8: INGRESOS | D8: EGRESOS | E8: SALDO
B9: SALDO EFECTIVO MES ANTERIOR | E9: ='CORTE SEPTIEMBRE 11-25 '!C25 -> 4718041.5 | I9: Total Consignado - Junio 2025 | J9: ='CORTE JUNIO 30-25'!J12 -> 4423867
A10: 45931 | B10: VENTA 30 JERSEY POR 50.000 ANIVERSARIO EN RALLY SUDAMERICANO | C10: 1913300 | E10: =E9+C10-D10 -> 6631341.5 | I10: Pendiente por cobro | J10: 690737
A11: 45932 | B11: VENTA 02 CAMISETAS LM | C11: 120000 | E11: =E10+C11-D11 -> 6751341.5
A12: 45933 | B12: VENTA 02 BALACLAVAS | C12: 40000 | E12: =E11+C12-D12 -> 6791341.5 | I12: Saldo a la fecha | J12: 4718042
A13: 45934 | B13: PAGO PARCHES APOYO CUBA | D13: 600000 | E13: =E12+C13-D13 -> 6191341.5
A14: 45935 | B14: VENTA 02 CAMISETAS LM ROBINSON | C14: 120000 | E14: =E13+C14-D14 -> 6311341.5
E15: =E14+C15-D15 -> 6311341.5
B16: TOTAL | C16: =SUM(C10:C15) -> 2193300 | D16: =SUM(D9:D15) -> 600000 | E16: =E15 -> 6311341.5 | I16: EFECTIVO PESOS | J16: 980000
I17: EFECTIVO DOLARES 229 | J17: 1093300
B19: SALDO EFECTIVO MES ANTERIOR | C19: =E9 -> 4718041.5 | J19: =SUM(J16:J17) -> 2073300
B20: INGRESOS | C20: =C16 -> 2193300 | J20: -160000
B21: dolares | C21: 0 | J21: =SUM(J19:J20) -> 1913300
B22: TOTAL INGRESOS | C22: =C19+C20 -> 6911341.5
B23: EGRESOS | C23: =+D16 -> 600000
B24: SALDO EN TESORERIA A LA FECHA | C24: =E16 -> 6311341.5
B27: ROBINSON ALEJANDRO GALVIS PARRA
B28: TESORERO LAMA MEDELLIN
